TOPSIS-Ankita-102017120
topsis
