Metadata-Version: 2.1
Name: TOPSIS-Ankita-102017120
Version: 1.4
Summary: This is a Python library for handling problems related to Multiple Criteria Decision Making(MCDM)
Home-page: UNKNOWN
Author: Ankita Sharma
Author-email: ankitasharma102002@gmail.com
License: MIT
Platform: UNKNOWN
Classifier: License :: OSI Approved :: MIT License
Classifier: Programming Language :: Python :: 3.6
Classifier: Programming Language :: Python :: 3.7
Classifier: Programming Language :: Python :: 3.8
License-File: LICENSE.txt
